Metadata-Version: 2.4
Name: proteorift
Version: 1.1.9
Summary: End-to-end machine learning pipeline for peptide database search
Author: ProteoRift Team
License: Creative Commons Attribution-NonCommercial-NoDerivatives 4.0 International Public License
Project-URL: Homepage, https://github.com/pcdslab/ProteoRift
Project-URL: Repository, https://github.com/pcdslab/ProteoRift
Keywords: proteomics,peptide,machine-learning,bioinformatics
Classifier: Development Status :: 4 - Beta
Classifier: Intended Audience :: Science/Research
Classifier: Topic :: Scientific/Engineering :: Bio-Informatics
Requires-Python: >=3.8
Requires-Dist: torch>=1.10.0
Requires-Dist: numpy>=1.19.0
Requires-Dist: pandas>=1.3.0
Requires-Dist: scikit-learn>=0.24.0
Requires-Dist: tqdm>=4.62.0
Requires-Dist: huggingface-hub>=0.19.0
Requires-Dist: progressbar2>=3.53.0
Provides-Extra: dev
Requires-Dist: pytest>=6.0; extra == "dev"
Requires-Dist: black>=21.0; extra == "dev"
Requires-Dist: flake8>=3.9; extra == "dev"
